Q1/alu.v
// Verilog modules for 32-bit ALU and Datapath (BLM2022 Ödev 1)
`define WORD_SIZE 32

// ZeroExtender: Extends a 1-bit input to 32 bits (for SLT result)
module ZeroExtender(
    input  wire       in,    // 1-bit input (Less indicator)
    output wire [31:0] out    // zero-extended 32-bit output
);
    assign out = {31'b0, in};
endmodule

// Adder: 32-bit addition
module Adder(
    input  wire [31:0] A,
    input  wire [31:0] B,
    output wire [31:0] Result
);
    assign Result = A + B;
endmodule

// Subtractor: 32-bit subtraction
module Subtractor(
    input  wire [31:0] A,
    input  wire [31:0] B,
    output wire [31:0] Result
);
    assign Result = A - B;
endmodule

// And32: bitwise AND
module And32(
    input  wire [31:0] A,
    input  wire [31:0] B,
    output wire [31:0] Result
);
    assign Result = A & B;
endmodule

// Xor32: bitwise XOR
module Xor32(
    input  wire [31:0] A,
    input  wire [31:0] B,
    output wire [31:0] Result
);
    assign Result = A ^ B;
endmodule

// SLT: set-on-less-than
module SLT(
    input  wire [31:0] A,
    input  wire [31:0] B,
    output wire [31:0] Result
);
    wire less_bit;
    assign less_bit = (A < B) ? 1'b1 : 1'b0;
    ZeroExtender ze(.in(less_bit), .out(Result));
endmodule

// Top-level ALU
module ALU(
    input  wire [31:0] A,
    input  wire [31:0] B,
    input  wire [2:0]  ALUControl,
    output reg  [31:0] Result,
    output wire        Zero
);
    wire [31:0] addRes, subRes, andRes, xorRes, sltRes;
    Adder       add(.A(A), .B(B),           .Result(addRes));
    Subtractor  sub(.A(A), .B(B),           .Result(subRes));
    And32       _and(.A(A), .B(B),          .Result(andRes));
    Xor32       _xor(.A(A), .B(B),          .Result(xorRes));
    SLT         slt(.A(A), .B(B),           .Result(sltRes));

    always @(*) begin
        case (ALUControl)
            3'b000: Result = addRes;
            3'b001: Result = subRes;
            3'b010: Result = andRes;
            3'b011: Result = xorRes;
            3'b101: Result = sltRes;
            default: Result = 32'b0;
        endcase
    end

    assign Zero = (Result == 32'b0);
endmodule

// Datapath: connects ALU and Register File
module Datapath(
    input  wire           clk,
    input  wire           rst,
    input  wire           wr,
    input  wire [2:0]     ALUControl,
    input  wire [1:0]     addr1,
    input  wire [1:0]     addr2,
    input  wire [1:0]     addr3,
    output wire           Zero
);
    wire [31:0] data1;
    wire [31:0] data2;
    wire [31:0] alu_result;

    // Register File instance
    regfile rf (
        .addr1(addr1),
        .addr2(addr2),
        .addr3(addr3),
        .data1(data1),
        .data2(data2),
        .data3(alu_result),
        .clk(clk),
        .wr(wr),
        .rst(rst)
    );

    // ALU instance
    ALU alu_unit (
        .A(data1),
        .B(data2),
        .ALUControl(ALUControl),
        .Result(alu_result),
        .Zero(Zero)
    );
endmodule

Q1/regfile.v
`timescale 1ns/1ps
`define WORD_SIZE 32
// 32-bit 4-kayıtlı Yazmaç Dosyası (Register File) Modülü
module regfile(addr1, addr2, addr3, data1, data2, data3, clk, wr, rst);
    input clk, wr, rst;
    input [1:0] addr1, addr2, addr3;
    input [`WORD_SIZE-1:0] data3;
    output [`WORD_SIZE-1:0] data1, data2;
    
    // 4 adet 32-bit yazmaç tanımı
    reg [`WORD_SIZE-1:0] register[3:0];
    
    // Başlangıç değerleri (yalnızca simülasyon için)
    initial register[0] = 32'h12345678;
    initial register[1] = 32'h9ABCDEF0;
    initial register[2] = 32'hFFFFFFFF;
    initial register[3] = 32'h00000001;
    
    // Asenkron okuma portları
    assign data1 = register[addr1];
    assign data2 = register[addr2];
    
    // Senkron yazma (pozitif clock kenarında)
    always @(posedge clk) begin
        if(rst) begin
            register[0] <= 32'b0;
            register[1] <= 32'b0;
            register[2] <= 32'b0;
            register[3] <= 32'b0;
        end
        if(wr) begin
            register[addr3] <= data3;
        end
    end
endmodule

Q1/datapath_tb.v
// Testbench for Datapath: verifies
// 1) R0 <- R1 + R2
// 2) R1 <- R2 AND R3
// 3) R3 <- R2 XOR R0
// 4) R2 <- R1 - R3

`timescale 1ns/1ps
module tb;
    reg        clk;
    reg        rst;
    reg        wr;
    reg  [2:0] ALUControl;
    reg  [1:0] addr1, addr2, addr3;
    wire       Zero;

    // Instantiate the datapath
    Datapath D (
        .clk(clk),
        .rst(rst),
        .wr(wr),
        .ALUControl(ALUControl),
        .addr1(addr1),
        .addr2(addr2),
        .addr3(addr3),
        .Zero(Zero)
    );

    // Clock generation: 10ns period
    initial clk = 0;
    always #5 clk = ~clk;

    initial begin
        // Enable waveform dump
        $dumpfile("datapath_tb.vcd");
        $dumpvars(0, tb);

        // Initialize signals
        rst = 0;
        wr  = 0;

        // 1) R0 <- R1 + R2
        #10;
        addr1      = 2'd1; // R1
        addr2      = 2'd2; // R2
        addr3      = 2'd0; // R0
        ALUControl = 3'b000; // ADD
        wr         = 1;
        #10; wr = 0;
        #2;
        $display("After ADD: R0 = %h", D.rf.register[0]);

        // 2) R1 <- R2 AND R3
        #10;
        addr1      = 2'd2; // R2
        addr2      = 2'd3; // R3
        addr3      = 2'd1; // R1
        ALUControl = 3'b010; // AND
        wr         = 1;
        #10; wr = 0;
        #2;
        $display("After AND: R1 = %h", D.rf.register[1]);

        // 3) R3 <- R2 XOR R0
        #10;
        addr1      = 2'd2; // R2
        addr2      = 2'd0; // R0
        addr3      = 2'd3; // R3
        ALUControl = 3'b011; // XOR
        wr         = 1;
        #10; wr = 0;
        #2;
        $display("After XOR: R3 = %h", D.rf.register[3]);

        // 4) R2 <- R1 - R3
        #10;
        addr1      = 2'd1; // R1
        addr2      = 2'd3; // R3
        addr3      = 2'd2; // R2
        ALUControl = 3'b001; // SUB
        wr         = 1;
        #10; wr = 0;
        #2;
        $display("After SUB: R2 = %h", D.rf.register[2]);

        $finish;
    end
endmodule

Q1/datapath_tb.vcd
$date
	Thu Apr 17 23:43:34 2025
$end
$version
	Icarus Verilog
$end
$timescale
	1ps
$end
$scope module tb $end
$var wire 1 ! Zero $end
$var reg 3 " ALUControl [2:0] $end
$var reg 2 # addr1 [1:0] $end
$var reg 2 $ addr2 [1:0] $end
$var reg 2 % addr3 [1:0] $end
$var reg 1 & clk $end
$var reg 1 ' rst $end
$var reg 1 ( wr $end
$scope module D $end
$var wire 3 ) ALUControl [2:0] $end
$var wire 2 * addr1 [1:0] $end
$var wire 2 + addr2 [1:0] $end
$var wire 2 , addr3 [1:0] $end
$var wire 1 & clk $end
$var wire 1 ' rst $end
$var wire 1 ( wr $end
$var wire 32 - data2 [31:0] $end
$var wire 32 . data1 [31:0] $end
$var wire 32 / alu_result [31:0] $end
$var wire 1 ! Zero $end
$scope module alu_unit $end
$var wire 3 0 ALUControl [2:0] $end
$var wire 32 1 xorRes [31:0] $end
$var wire 32 2 subRes [31:0] $end
$var wire 32 3 sltRes [31:0] $end
$var wire 32 4 andRes [31:0] $end
$var wire 32 5 addRes [31:0] $end
$var wire 1 ! Zero $end
$var wire 32 6 B [31:0] $end
$var wire 32 7 A [31:0] $end
$var reg 32 8 Result [31:0] $end
$scope module _and $end
$var wire 32 9 Result [31:0] $end
$var wire 32 : B [31:0] $end
$var wire 32 ; A [31:0] $end
$upscope $end
$scope module _xor $end
$var wire 32 < Result [31:0] $end
$var wire 32 = B [31:0] $end
$var wire 32 > A [31:0] $end
$upscope $end
$scope module add $end
$var wire 32 ? Result [31:0] $end
$var wire 32 @ B [31:0] $end
$var wire 32 A A [31:0] $end
$upscope $end
$scope module slt $end
$var wire 1 B less_bit $end
$var wire 32 C Result [31:0] $end
$var wire 32 D B [31:0] $end
$var wire 32 E A [31:0] $end
$scope module ze $end
$var wire 1 B in $end
$var wire 32 F out [31:0] $end
$upscope $end
$upscope $end
$scope module sub $end
$var wire 32 G Result [31:0] $end
$var wire 32 H B [31:0] $end
$var wire 32 I A [31:0] $end
$upscope $end
$upscope $end
$scope module rf $end
$var wire 2 J addr1 [1:0] $end
$var wire 2 K addr2 [1:0] $end
$var wire 2 L addr3 [1:0] $end
$var wire 1 & clk $end
$var wire 32 M data1 [31:0] $end
$var wire 32 N data2 [31:0] $end
$var wire 32 O data3 [31:0] $end
$var wire 1 ' rst $end
$var wire 1 ( wr $end
$upscope $end
$upscope $end
$upscope $end
$enddefinitions $end
$comment Show the parameter values. $end
$dumpall
$end
#0
$dumpvars
b0 O
bx N
bx M
bx L
bx K
bx J
bx I
bx H
bx G
b0x F
bx E
bx D
b0x C
xB
bx A
bx @
bx ?
bx >
bx =
bx <
bx ;
bx :
bx 9
b0 8
bx 7
bx 6
bx 5
bx 4
b0x 3
bx 2
bx 1
bx 0
b0 /
bx .
bx -
bx ,
bx +
bx *
bx )
0(
0'
0&
bx %
bx $
bx #
bx "
1!
$end
#5000
1&
#10000
b1 3
b1 C
b1 F
1B
0!
b10011010101111001101111011101111 /
b10011010101111001101111011101111 8
b10011010101111001101111011101111 O
b1100101010000110010000100001111 1
b1100101010000110010000100001111 <
b10011010101111001101111011110000 4
b10011010101111001101111011110000 9
0&
1(
b0 "
b0 )
b0 0
b0 %
b0 ,
b0 L
b10011010101111001101111011110001 2
b10011010101111001101111011110001 G
b10011010101111001101111011101111 5
b10011010101111001101111011101111 ?
b11111111111111111111111111111111 -
b11111111111111111111111111111111 6
b11111111111111111111111111111111 :
b11111111111111111111111111111111 =
b11111111111111111111111111111111 @
b11111111111111111111111111111111 D
b11111111111111111111111111111111 H
b11111111111111111111111111111111 N
b10 $
b10 +
b10 K
b10011010101111001101111011110000 .
b10011010101111001101111011110000 7
b10011010101111001101111011110000 ;
b10011010101111001101111011110000 >
b10011010101111001101111011110000 A
b10011010101111001101111011110000 E
b10011010101111001101111011110000 I
b10011010101111001101111011110000 M
b1 #
b1 *
b1 J
#15000
1&
#20000
0&
0(
#25000
1&
#30000
0&
#32000
b0 3
b0 C
b0 F
0B
b1 /
b1 8
b1 O
b11111111111111111111111111111110 1
b11111111111111111111111111111110 <
b1 4
b1 9
1(
b10 "
b10 )
b10 0
b1 %
b1 ,
b1 L
b1 -
b1 6
b1 :
b1 =
b1 @
b1 D
b1 H
b1 N
b11 $
b11 +
b11 K
b11111111111111111111111111111110 2
b11111111111111111111111111111110 G
b0 5
b0 ?
b11111111111111111111111111111111 .
b11111111111111111111111111111111 7
b11111111111111111111111111111111 ;
b11111111111111111111111111111111 >
b11111111111111111111111111111111 A
b11111111111111111111111111111111 E
b11111111111111111111111111111111 I
b11111111111111111111111111111111 M
b10 #
b10 *
b10 J
#35000
1&
#40000
0&
#42000
0(
#45000
1&
#50000
0&
#54000
b1100101010000110010000100010000 /
b1100101010000110010000100010000 8
b1100101010000110010000100010000 O
b1100101010000110010000100010000 1
b1100101010000110010000100010000 <
b10011010101111001101111011101111 4
b10011010101111001101111011101111 9
1(
b11 "
b11 )
b11 0
b11 %
b11 ,
b11 L
b1100101010000110010000100010000 2
b1100101010000110010000100010000 G
b10011010101111001101111011101110 5
b10011010101111001101111011101110 ?
b10011010101111001101111011101111 -
b10011010101111001101111011101111 6
b10011010101111001101111011101111 :
b10011010101111001101111011101111 =
b10011010101111001101111011101111 @
b10011010101111001101111011101111 D
b10011010101111001101111011101111 H
b10011010101111001101111011101111 N
b0 $
b0 +
b0 K
#55000
1&
#60000
0&
#64000
0(
#65000
1&
#70000
0&
#75000
1&
#76000
b1 3
b1 C
b1 F
1B
b10011010101111001101111011110001 /
b10011010101111001101111011110001 8
b10011010101111001101111011110001 O
b1100101010000110010000100010001 1
b1100101010000110010000100010001 <
b0 4
b0 9
1(
b1 "
b1 )
b1 0
b10 %
b10 ,
b10 L
b1100101010000110010000100010000 -
b1100101010000110010000100010000 6
b1100101010000110010000100010000 :
b1100101010000110010000100010000 =
b1100101010000110010000100010000 @
b1100101010000110010000100010000 D
b1100101010000110010000100010000 H
b1100101010000110010000100010000 N
b11 $
b11 +
b11 K
b10011010101111001101111011110001 2
b10011010101111001101111011110001 G
b1100101010000110010000100010001 5
b1100101010000110010000100010001 ?
b1 .
b1 7
b1 ;
b1 >
b1 A
b1 E
b1 I
b1 M
b1 #
b1 *
b1 J
#80000
0&
#85000
1&
#86000
0(
